LICENSE
MANIFEST.in
README
setup.py
Density_Sampling.egg-info/PKG-INFO
Density_Sampling.egg-info/SOURCES.txt
Density_Sampling.egg-info/dependency_links.txt
Density_Sampling.egg-info/requires.txt
Density_Sampling.egg-info/top_level.txt
src/Density_Sampling/Density_Sampling.py
src/Density_Sampling/__init__.py
src/Density_Sampling/FLANN/CMakeLists.txt
src/Density_Sampling/FLANN/COPYING
src/Density_Sampling/FLANN/ChangeLog
src/Density_Sampling/FLANN/README.md
src/Density_Sampling/FLANN/bin/download_checkmd5.py
src/Density_Sampling/FLANN/bin/indent.sh
src/Density_Sampling/FLANN/bin/make_release.sh
src/Density_Sampling/FLANN/bin/run_test.py
src/Density_Sampling/FLANN/bin/uncrustify.cfg
src/Density_Sampling/FLANN/cmake/CMakeLists.txt
src/Density_Sampling/FLANN/cmake/FindFlann.cmake
src/Density_Sampling/FLANN/cmake/UseLATEX.cmake
src/Density_Sampling/FLANN/cmake/flann.pc.in
src/Density_Sampling/FLANN/cmake/flann_utils.cmake
src/Density_Sampling/FLANN/cmake/uninstall_target.cmake.in
src/Density_Sampling/FLANN/doc/CMakeLists.txt
src/Density_Sampling/FLANN/doc/manual.pdf
src/Density_Sampling/FLANN/doc/manual.tex
src/Density_Sampling/FLANN/doc/references.bib
src/Density_Sampling/FLANN/doc/images/cmake-gui.png
src/Density_Sampling/FLANN/examples/CMakeLists.txt
src/Density_Sampling/FLANN/examples/README
src/Density_Sampling/FLANN/examples/flann_example.c
src/Density_Sampling/FLANN/examples/flann_example.cpp
src/Density_Sampling/FLANN/examples/flann_example_mpi.cpp
src/Density_Sampling/FLANN/src/CMakeLists.txt
src/Density_Sampling/FLANN/src/cpp/CMakeLists.txt
src/Density_Sampling/FLANN/src/cpp/flann/config.h
src/Density_Sampling/FLANN/src/cpp/flann/config.h.in
src/Density_Sampling/FLANN/src/cpp/flann/defines.h
src/Density_Sampling/FLANN/src/cpp/flann/flann.cpp
src/Density_Sampling/FLANN/src/cpp/flann/flann.h
src/Density_Sampling/FLANN/src/cpp/flann/flann.hpp
src/Density_Sampling/FLANN/src/cpp/flann/flann_cpp.cpp
src/Density_Sampling/FLANN/src/cpp/flann/general.h
src/Density_Sampling/FLANN/src/cpp/flann/algorithms/all_indices.h
src/Density_Sampling/FLANN/src/cpp/flann/algorithms/autotuned_index.h
src/Density_Sampling/FLANN/src/cpp/flann/algorithms/center_chooser.h
