Metadata-Version: 1.1
Name: Density-Sampling
Version: 1.3
Summary: For a dataset comprising a mixture of rare and common populations, density sampling gives equal weights to the representatives of those distinct populations.
Home-page: https://github.com/GGiecold/Density_Sampling
Author: Gregory Giecold
Author-email: ggiecold@jimmy.harvard.edu
License: MIT License
Download-URL: https://github.com/GGiecold/Density_Sampling
Platform: Any
Classifier: Development Status :: 4 - Beta
Classifier: Environment :: Console
Classifier: Intended Audience :: End Users/Desktop
Classifier: Intended Audience :: Developers
Classifier: Intended Audience :: Science/Research
Classifier: License :: OSI Approved :: MIT License
Classifier: Natural Language :: English
Classifier: Operating System :: MacOS :: MacOS X
Classifier: Operating System :: POSIX
Classifier: Programming Language :: Python :: 2.7
Classifier: Topic :: Scientific/Engineering
Classifier: Topic :: Scientific/Engineering :: Visualization
Classifier: Topic :: Scientific/Engineering :: Mathematics
